keepstart
